odoo10_addon_module_auto_update-10.0.2.0.3-py2.7-nspkg.pth
odoo/addons/module_auto_update/README.rst
odoo/addons/module_auto_update/__init__.py
odoo/addons/module_auto_update/__manifest__.py
odoo/addons/module_auto_update/addon_hash.py
odoo/addons/module_auto_update/hooks.py
odoo/addons/module_auto_update/data/cron_data_deprecated.xml
odoo/addons/module_auto_update/i18n/ca.po
odoo/addons/module_auto_update/i18n/de.po
odoo/addons/module_auto_update/i18n/es.po
odoo/addons/module_auto_update/i18n/es_MX.po
odoo/addons/module_auto_update/i18n/hr.po
odoo/addons/module_auto_update/i18n/it.po
odoo/addons/module_auto_update/i18n/nl_NL.po
odoo/addons/module_auto_update/i18n/pt_BR.po
odoo/addons/module_auto_update/i18n/sl.po
odoo/addons/module_auto_update/i18n/tr.po
odoo/addons/module_auto_update/migrations/10.0.2.0.0/pre-migrate.py
odoo/addons/module_auto_update/models/__init__.py
odoo/addons/module_auto_update/models/module.py
odoo/addons/module_auto_update/models/module_deprecated.py
odoo/addons/module_auto_update/tests/__init__.py
odoo/addons/module_auto_update/tests/test_addon_hash.py
odoo/addons/module_auto_update/tests/test_module.py
odoo/addons/module_auto_update/tests/test_module_deprecated.py
odoo/addons/module_auto_update/tests/test_module_upgrade_deprecated.py
odoo/addons/module_auto_update/tests/sample_module/README.rst
odoo/addons/module_auto_update/tests/sample_module/data/f1.xml
odoo/addons/module_auto_update/tests/sample_module/data/f2.xml
odoo/addons/module_auto_update/tests/sample_module/i18n/en.po
odoo/addons/module_auto_update/tests/sample_module/i18n/en_US.po
odoo/addons/module_auto_update/tests/sample_module/i18n/fr.po
odoo/addons/module_auto_update/tests/sample_module/i18n/fr_BE.po
odoo/addons/module_auto_update/tests/sample_module/i18n/test.pot
odoo/addons/module_auto_update/tests/sample_module/i18n_extra/en.po
odoo/addons/module_auto_update/tests/sample_module/i18n_extra/fr.po
odoo10_addon_module_auto_update-10.0.2.0.3.dist-info/DESCRIPTION.rst
odoo10_addon_module_auto_update-10.0.2.0.3.dist-info/METADATA
odoo10_addon_module_auto_update-10.0.2.0.3.dist-info/RECORD
odoo10_addon_module_auto_update-10.0.2.0.3.dist-info/WHEEL
odoo10_addon_module_auto_update-10.0.2.0.3.dist-info/metadata.json
odoo10_addon_module_auto_update-10.0.2.0.3.dist-info/namespace_packages.txt
odoo10_addon_module_auto_update-10.0.2.0.3.dist-info/top_level.txt
