Metadata-Version: 2.0
Name: odoo10-addon-module-auto-update
Version: 10.0.2.0.3
Summary: Automatically update Odoo modules
Home-page: https://github.com/OCA/server-tools
Author: LasLabs, Juan José Scarafía, Tecnativa, ACSONE SA/NV, Odoo Community Association (OCA)
Author-email: support@odoo-community.org
License: LGPL-3
Platform: UNKNOWN
Classifier: Programming Language :: Python
Classifier: Framework :: Odoo
Classifier: License :: OSI Approved :: GNU Lesser General Public License v3 (LGPLv3)
Requires-Python: ~=2.7
Requires-Dist: odoo (<10.1dev,>=10.0)
